stawp/__init__.py
stawp/build.py
stawp/cli.py
stawp/module.py
stawp/move.py
stawp/page.py
stawp/modules/__init__.py
stawp/modules/gallery.py
stawp/modules/menu.py
stawp/modules/sitemap.py
stawp-3.0.2.dist-info/licenses/LICENSE
stawp-3.0.2.dist-info/METADATA
stawp-3.0.2.dist-info/WHEEL
stawp-3.0.2.dist-info/entry_points.txt
stawp-3.0.2.dist-info/top_level.txt
stawp-3.0.2.dist-info/RECORD
