Metadata-Version: 2.4
Name: stawp
Version: 3.0.2
Summary: STAtic Website Producer
Author-email: Matt Wisniewski <stawp@mattw.life>
License: MIT
Project-URL: homepage, https://github.com/polishmatt/stawp/
Keywords: static,website
Classifier: Development Status :: 5 - Production/Stable
Classifier: Environment :: Console
Classifier: Intended Audience :: Developers
Classifier: License :: OSI Approved :: MIT License
Classifier: Programming Language :: Python :: 3.10
Classifier: Programming Language :: Python :: 3.11
Classifier: Programming Language :: Python :: 3.12
Classifier: Programming Language :: Python :: 3.13
Requires-Python: >=3.10.0
License-File: LICENSE
Requires-Dist: Pillow~=11.3
Requires-Dist: pyaml~=25.7
Requires-Dist: click~=8.2
Provides-Extra: tests
Requires-Dist: pytest; extra == "tests"
Dynamic: license-file
